MANIFEST.in
README.rst
setup.cfg
setup.py
bpolicy/__init__.py
bpolicy/base.py
bpolicy/clock.py
bpolicy/consts.py
bpolicy/error.py
bpolicy/generationed.py
bpolicy/rated.py
bpolicy/store.py
bpolicy/utils.py
bpolicy.egg-info/PKG-INFO
bpolicy.egg-info/SOURCES.txt
bpolicy.egg-info/dependency_links.txt
bpolicy.egg-info/requires.txt
bpolicy.egg-info/top_level.txt
tests/__init__.py
tests/test_clock_policy.py
tests/test_combined_policy.py
tests/test_generationed_policy.py
tests/test_rated_policy.py