Metadata-Version: 1.1
Name: bpolicy
Version: 0.3.2
Summary: A collection of basic policies for resources anti-spammer
Home-page: https://github.com/mapix/bpolicy
Author: mapix
Author-email: mapix.me@gmail.com
License: MIT
Platform: UNKNOWN
Classifier: Programming Language :: Python :: 2.6
Classifier: Programming Language :: Python :: 2.7
Classifier: Programming Language :: Python :: 3
